LICENSE.txt
MANIFEST.in
README.md
setup.py
teleg_api_bot.egg-info/PKG-INFO
teleg_api_bot.egg-info/SOURCES.txt
teleg_api_bot.egg-info/dependency_links.txt
teleg_api_bot.egg-info/requires.txt
teleg_api_bot.egg-info/top_level.txt
telegapi/TC.py
telegapi/__init__.py
telegapi/config.yml
telegapi/exceptions.py
telegapi/logger.py
telegapi/telegbot.py
telegapi/utils.py