Metadata-Version: 1.1
Name: teleg-api-bot
Version: 0.0.111
Summary: Wrapper to Telegram bots API
Home-page: https://github.com/LibreLabUCM/teleg-api-bot
Author: LibreLabUCM
Author-email: librelabucm@googlegroups.com
License: GNU General Public License (GPL)
Platform: UNKNOWN
Classifier: Programming Language :: Python :: 3
Classifier: License :: OSI Approved :: GNU General Public License (GPL)
Classifier: Operating System :: OS Independent
Classifier: Development Status :: 3 - Alpha
Classifier: Environment :: Console
Classifier: Intended Audience :: Developers
Classifier: Topic :: Software Development :: Libraries :: Python Modules
